{"P1": {"labels": ["\u5de5\u5177"], "postTitle": "Cloudflare\u5168\u7403CDN\u8282\u70b9\u5730\u5740", "postUrl": "post/Cloudflare-quan-qiu-CDN-jie-dian-di-zhi.html", "createdDate": "2025-11-08", "dateLabelColor": "#0969da"}, "labelColorDict": {"bug": "#d73a4a", "documentation": "#0075ca", "duplicate": "#cfd3d7", "enhancement": "#a2eeef", "good first issue": "#7057ff", "help wanted": "#008672", "invalid": "#e4e669", "question": "#d876e3", "wontfix": "#ffffff", "\u5de5\u5177": "#feb433", "\u65e5\u5e38": "#c9c9ee", "\u95f2\u804a": "#234ab6"}}